evoml/framework/__init__.py
evoml/framework/constant.py
evoml/framework/evocc.py
evoml/framework/classification/__init__.py
evoml/framework/classification/_base.py
evoml/framework/datasets/__init__.py
evoml/framework/datasets/_base.py
evoml/framework/datasets/data/Blood.csv
evoml/framework/datasets/data/XXX.csv
evoml/framework/datasets/data/__init__.py
evoml/framework/datasets/data/aggregation.csv
evoml/framework/datasets/data/aniso.csv
evoml/framework/datasets/data/appendicitis.csv
evoml/framework/datasets/data/balance.csv
evoml/framework/datasets/data/banknote.csv
evoml/framework/datasets/data/blobs.csv
evoml/framework/datasets/data/circles.csv
evoml/framework/datasets/data/diagnosis_II.csv
evoml/framework/datasets/data/ecoli.csv
evoml/framework/datasets/data/flame.csv
evoml/framework/datasets/data/glass.csv
evoml/framework/datasets/data/heart.csv
evoml/framework/datasets/data/ionosphere.csv
evoml/framework/datasets/data/iris.csv
evoml/framework/datasets/data/iris2D.csv
evoml/framework/datasets/data/jain.csv
evoml/framework/datasets/data/liver.csv
evoml/framework/datasets/data/moons.csv
evoml/framework/datasets/data/mouse.csv
evoml/framework/datasets/data/pathbased.csv
evoml/framework/datasets/data/seeds.csv
evoml/framework/datasets/data/smiley.csv
evoml/framework/datasets/data/sonar.csv
evoml/framework/datasets/data/varied.csv
evoml/framework/datasets/data/vary-density.csv
evoml/framework/datasets/data/vertebral2.csv
evoml/framework/datasets/data/vertebral3.csv
evoml/framework/datasets/data/wdbc.csv
evoml/framework/datasets/data/wine.csv
evoml/framework/metrics/__init__.py
evoml/framework/metrics/_base.py
evoml/framework/utils/__init__.py
evoml/framework/utils/_base.py
evoml.framework-1.0.3.dist-info/LICENSE
evoml.framework-1.0.3.dist-info/METADATA
evoml.framework-1.0.3.dist-info/WHEEL
evoml.framework-1.0.3.dist-info/top_level.txt
evoml.framework-1.0.3.dist-info/RECORD
