Metadata-Version: 2.1
Name: evoml.framework
Version: 1.0.3
Summary: An Open-Source Classification-Based Nature-Inspired Optimization Clustering Framework in Python
License: MIT
Keywords: iot
Platform: UNKNOWN
Classifier: Programming Language :: Python :: 3
Classifier: Programming Language :: Python :: 3.7
License-File: LICENSE
Requires-Dist: pandas
Requires-Dist: numpy
Requires-Dist: imbalanced-learn
Requires-Dist: matplotlib
